.coveragerc
AUTHORS
ChangeLog
MANIFEST.in
README.md
requirements.txt
setup.cfg
setup.py
tox.ini
ethexporter/__init__.py
ethexporter/cli.py
ethexporter/defaults.yml
ethexporter.egg-info/PKG-INFO
ethexporter.egg-info/SOURCES.txt
ethexporter.egg-info/dependency_links.txt
ethexporter.egg-info/entry_points.txt
ethexporter.egg-info/not-zip-safe
ethexporter.egg-info/pbr.json
ethexporter.egg-info/requires.txt
ethexporter.egg-info/top_level.txt
ethexporter/scraper/__init__.py
ethexporter/scraper/web3.py
tests/test_context.py
tests/test_scraper_core.py
tests/test_scraper_web3.py